[
  {
    "id": 1,
    "title": "123",
    "heading": "23",
    "aop_number": "23231",
    "publish_date": "2026-02-17",
    "start_date": "",
    "internal_number": "",
    "content": "23",
    "files": [],
    "pdf_files": [
      {
        "name": "AZZ (1)",
        "url": "/pdf/20260203_204717_-_Copy.pdf",
        "filename": "20260203_204717_-_Copy.pdf"
      },
      {
        "name": "AZZ (2)",
        "url": "/pdf/20260203_204717_pdf",
        "filename": "20260203_204717_pdf"
      }
    ],
    "source_url": "",
    "imported_at": "",
    "page_id": 1,
    "date": "2026-02-03 20:47:17"
  }
]